[{"round":"Finals","rowid":5,"data":[{"winner_name":"Bohdan Ulihrach","loser_name":"Javier Sanchez","score":"62 62"}]},{"round":"Semi-Finals","rowid":4,"data":[{"winner_name":"Javier Sanchez","loser_name":"Albert Portas","score":"36 61 64"},{"winner_name":"Bohdan Ulihrach","loser_name":"Nicklas Kulti","score":"64 64"}]},{"round":"Quarter-Finals","rowid":3,"data":[{"winner_name":"Javier Sanchez","loser_name":"Marc Rosset","score":"64 64"},{"winner_name":"Nicklas Kulti","loser_name":"Mariano Zabaleta","score":"62 61"},{"winner_name":"Albert Portas","loser_name":"Karim Alami","score":"46 764 61"},{"winner_name":"Bohdan Ulihrach","loser_name":"Gaston Etlis","score":"63 75"}]},{"round":"Round of 16","rowid":2,"data":[{"winner_name":"Marc Rosset","loser_name":"David Skoch","score":"763 75"},{"winner_name":"Albert Portas","loser_name":"Karol Kucera","score":"62 26 60"},{"winner_name":"Bohdan Ulihrach","loser_name":"Slava Dosedel","score":"06 62 75"},{"winner_name":"Javier Sanchez","loser_name":"David Rikl","score":"766 61"},{"winner_name":"Karim Alami","loser_name":"Hernan Gumy","score":"62 64"},{"winner_name":"Gaston Etlis","loser_name":"Oleg Ogorodov","score":"64 62"},{"winner_name":"Nicklas Kulti","loser_name":"Jiri Vanek","score":"60 64"},{"winner_name":"Mariano Zabaleta","loser_name":"Sergio Cortes","score":"64 64"}]},{"round":"Round of 32","rowid":1,"data":[{"winner_name":"Marc Rosset","loser_name":"Jaroslav Bulant","score":"61 16 64"},{"winner_name":"Nicklas Kulti","loser_name":"Andrei Medvedev","score":"75 (RET)"},{"winner_name":"Karol Kucera","loser_name":"Andrei Cherkasov","score":"63 16 61"},{"winner_name":"Hernan Gumy","loser_name":"Christian Ruud","score":"46 61 63"},{"winner_name":"Slava Dosedel","loser_name":"Henri Leconte","score":"61 63"},{"winner_name":"Javier Sanchez","loser_name":"Ronald Agenor","score":"46 62 63"},{"winner_name":"Sergio Cortes","loser_name":"Jaime Yzaga","score":"46 766 63"},{"winner_name":"Karim Alami","loser_name":"David Miketa","score":"762 60"},{"winner_name":"Gaston Etlis","loser_name":"Oscar Martinez","score":"64 64"},{"winner_name":"Oleg Ogorodov","loser_name":"Franco Davin","score":"63 36 63"},{"winner_name":"Albert Portas","loser_name":"Marcos Aurelio Gorriz","score":"62 64"},{"winner_name":"David Rikl","loser_name":"Jiri Novak","score":"63 61"},{"winner_name":"David Skoch","loser_name":"Jan Kroslak","score":"06 61 62"},{"winner_name":"Bohdan Ulihrach","loser_name":"Marco Meneschincheri","score":"64 61"},{"winner_name":"Jiri Vanek","loser_name":"Radomir Vasek","score":"64 46 64"},{"winner_name":"Mariano Zabaleta","loser_name":"Wojtek Kowalski","score":"64 16 763"}]}]
