[{"round":"Finals","rowid":5,"data":[{"winner_name":"Denis Gremelmayr","loser_name":"Roko Karanusic","score":"(W/O)"}]},{"round":"Semi-Finals","rowid":4,"data":[{"winner_name":"Roko Karanusic","loser_name":"Igor Kunitsyn","score":"61 61"},{"winner_name":"Denis Gremelmayr","loser_name":"Dominik Meffert","score":"57 62 766"}]},{"round":"Quarter-Finals","rowid":3,"data":[{"winner_name":"Igor Kunitsyn","loser_name":"Mikhail Ledovskikh","score":"764 62"},{"winner_name":"Denis Gremelmayr","loser_name":"Andrey Golubev","score":"62 63"},{"winner_name":"Roko Karanusic","loser_name":"Philipp Petzschner","score":"763 62"},{"winner_name":"Dominik Meffert","loser_name":"Marc Meigel","score":"61 763"}]},{"round":"Round of 16","rowid":2,"data":[{"winner_name":"Igor Kunitsyn","loser_name":"Jesse Huta Galung","score":"46 62 763"},{"winner_name":"Denis Gremelmayr","loser_name":"Daniel Brands","score":"62 63"},{"winner_name":"Roko Karanusic","loser_name":"Andis Juska","score":"62 61"},{"winner_name":"Philipp Petzschner","loser_name":"Igor Sijsling","score":"61 62"},{"winner_name":"Andrey Golubev","loser_name":"Marcel Zimmermann","score":"763 63"},{"winner_name":"Mikhail Ledovskikh","loser_name":"Peter Gojowczyk","score":"75 62"},{"winner_name":"Dominik Meffert","loser_name":"Wesley Moodie","score":"63 62"},{"winner_name":"Marc Meigel","loser_name":"Denis Matsukevich","score":"761 62"}]},{"round":"Round of 32","rowid":1,"data":[{"winner_name":"Dominik Meffert","loser_name":"Rainer Schuettler","score":"62 64"},{"winner_name":"Igor Kunitsyn","loser_name":"Alexandr Dolgopolov","score":"63 63"},{"winner_name":"Denis Gremelmayr","loser_name":"Matthias Bachinger","score":"60 16 61"},{"winner_name":"Roko Karanusic","loser_name":"Jan Mertl","score":"63 64"},{"winner_name":"Peter Gojowczyk","loser_name":"Aisam-Ul-Haq Qureshi","score":"64 61"},{"winner_name":"Marc Meigel","loser_name":"Alexander Peya","score":"63 26 765"},{"winner_name":"Philipp Petzschner","loser_name":"Tobias Kamke","score":"62 62"},{"winner_name":"Andrey Golubev","loser_name":"Andreas Beck","score":"62 62"},{"winner_name":"Daniel Brands","loser_name":"Michal Schmid","score":"62 62"},{"winner_name":"Jesse Huta Galung","loser_name":"Alexander Kudryavtsev","score":"61 36 62"},{"winner_name":"Andis Juska","loser_name":"Peter Wessels","score":"46 75 63"},{"winner_name":"Mikhail Ledovskikh","loser_name":"Evgeny Kirillov","score":"63 36 75"},{"winner_name":"Denis Matsukevich","loser_name":"Marko Tkalec","score":"675 62 63"},{"winner_name":"Wesley Moodie","loser_name":"Juho Paukku","score":"46 64 63"},{"winner_name":"Igor Sijsling","loser_name":"Simon Stadler","score":"46 64 64"},{"winner_name":"Marcel Zimmermann","loser_name":"Jan Vacek","score":"62 63"}]}]
