[{"tourney_name":"Dallas WCT","surface":"Carpet","data":[{"round":"Quarter-Finals","Date":"0001-01-01","data":[{"winner_name":"Bjorn Borg","loser_name":"Eddie Dibbs","score":"36 63 64 62"},{"winner_name":"Harold Solomon","loser_name":"Arthur Ashe","score":"75 36 61 63"},{"winner_name":"Dick Stockton","loser_name":"Raul Ramirez","score":"63 76 76"},{"winner_name":"Guillermo Vilas","loser_name":"Robert Lutz","score":"57 61 61 62"}]},{"round":"Semi-Finals","Date":"0001-01-02","data":[{"winner_name":"Bjorn Borg","loser_name":"Harold Solomon","score":"75 60 63"},{"winner_name":"Guillermo Vilas","loser_name":"Dick Stockton","score":"75 64 61"}]},{"round":"Final","Date":"0001-01-03","data":[{"winner_name":"Bjorn Borg","loser_name":"Guillermo Vilas","score":"16 61 75 61"}]}]}]
