[{"round":"Finals","rowid":5,"data":[{"winner_name":"Gaston Gaudio","loser_name":"Jarkko Nieminen","score":"62 63"}]},{"round":"Semi-Finals","rowid":4,"data":[{"winner_name":"Jarkko Nieminen","loser_name":"Mariano Zabaleta","score":"61 63"},{"winner_name":"Gaston Gaudio","loser_name":"Agustin Calleri","score":"46 63 62"}]},{"round":"Quarter-Finals","rowid":3,"data":[{"winner_name":"Gaston Gaudio","loser_name":"Gustavo Kuerten","score":"75 60"},{"winner_name":"Jarkko Nieminen","loser_name":"Dominik Hrbaty","score":"64 762"},{"winner_name":"Agustin Calleri","loser_name":"Olivier Rochus","score":"63 06 61"},{"winner_name":"Mariano Zabaleta","loser_name":"David Sanchez","score":"75 63"}]},{"round":"Round of 16","rowid":2,"data":[{"winner_name":"Gustavo Kuerten","loser_name":"Magnus Norman","score":"61 57 63"},{"winner_name":"Jarkko Nieminen","loser_name":"Galo Blanco","score":"60 63"},{"winner_name":"Agustin Calleri","loser_name":"Juan Balcells","score":"63 61"},{"winner_name":"David Sanchez","loser_name":"Albert Montanes","score":"765 64"},{"winner_name":"Dominik Hrbaty","loser_name":"Christophe Rochus","score":"64 64"},{"winner_name":"Gaston Gaudio","loser_name":"Cedric Pioline","score":"61 63"},{"winner_name":"Olivier Rochus","loser_name":"Rafael Nadal","score":"62 62"},{"winner_name":"Mariano Zabaleta","loser_name":"Jean-Francois Bachelot","score":"46 75 60"}]},{"round":"Round of 32","rowid":1,"data":[{"winner_name":"Gustavo Kuerten","loser_name":"Nikolay Davydenko","score":"62 63"},{"winner_name":"Mariano Zabaleta","loser_name":"Albert Portas","score":"61 64"},{"winner_name":"Olivier Rochus","loser_name":"Sjeng Schalken","score":"62 36 75"},{"winner_name":"Jarkko Nieminen","loser_name":"Andre Sa","score":"61 62"},{"winner_name":"Agustin Calleri","loser_name":"Markus Hipfl","score":"60 62"},{"winner_name":"Albert Montanes","loser_name":"Michael Russell","score":"675 765 64"},{"winner_name":"Dominik Hrbaty","loser_name":"Guillermo Coria","score":"60 10 (RET)"},{"winner_name":"Gaston Gaudio","loser_name":"Fernando Vicente","score":"06 63 62"},{"winner_name":"Jean-Francois Bachelot","loser_name":"Mario Radic","score":"64 62"},{"winner_name":"Juan Balcells","loser_name":"Antony Dupuis","score":"75 64"},{"winner_name":"Galo Blanco","loser_name":"Hyung-Taik Lee","score":"63 63"},{"winner_name":"Rafael Nadal","loser_name":"Ramon Delgado","score":"64 64"},{"winner_name":"Magnus Norman","loser_name":"Mariano Albert-Ferrando","score":"63 64"},{"winner_name":"Cedric Pioline","loser_name":"Jose Acasuso","score":"63 674 64"},{"winner_name":"Christophe Rochus","loser_name":"Kristian Pless","score":"767 26 62"},{"winner_name":"David Sanchez","loser_name":"Paradorn Srichaphan","score":"62 64"}]}]
