[{"round":"Finals","rowid":8,"data":[{"winner_name":"Marcos Baghdatis","loser_name":"Farrukh Dustov","score":"766 63"}]},{"round":"Semi-Finals","rowid":7,"data":[{"winner_name":"Marcos Baghdatis","loser_name":"Ruben Bemelmans","score":"46 61 764"},{"winner_name":"Farrukh Dustov","loser_name":"James Ward","score":"764 63"}]},{"round":"Quarter-Finals","rowid":6,"data":[{"winner_name":"Marcos Baghdatis","loser_name":"Taro Daniel","score":"64 762"},{"winner_name":"Farrukh Dustov","loser_name":"Austin Krajicek","score":"46 61 60"},{"winner_name":"James Ward","loser_name":"Thanasi Kokkinakis","score":"63 64"},{"winner_name":"Ruben Bemelmans","loser_name":"Alex Bogomolov Jr.","score":"61 63"}]},{"round":"Round of 16","rowid":5,"data":[{"winner_name":"Marcos Baghdatis","loser_name":"Chase Buchanan","score":"765 63"},{"winner_name":"Farrukh Dustov","loser_name":"Andrea Collarini","score":"62 62"},{"winner_name":"Taro Daniel","loser_name":"Daniel Evans","score":"64 75"},{"winner_name":"James Ward","loser_name":"Wayne Odesnik","score":"(W/O)"},{"winner_name":"Alex Bogomolov Jr.","loser_name":"Vincent Millot","score":"63 62"},{"winner_name":"Ruben Bemelmans","loser_name":"Yasutaka Uchiyama","score":"64 767"},{"winner_name":"Thanasi Kokkinakis","loser_name":"Rik De Voest","score":"64 673 64"},{"winner_name":"Austin Krajicek","loser_name":"Yoshihito Nishioka","score":"64 64"}]},{"round":"Round of 32","rowid":4,"data":[{"winner_name":"Marcos Baghdatis","loser_name":"John-Patrick Smith","score":"64 57 75"},{"winner_name":"Thanasi Kokkinakis","loser_name":"Jimmy Wang","score":"75 64"},{"winner_name":"Yasutaka Uchiyama","loser_name":"Ante Pavic","score":"63 64"},{"winner_name":"Farrukh Dustov","loser_name":"Rhyne Williams","score":"60 36 64"},{"winner_name":"Daniel Evans","loser_name":"Matt Reid","score":"64 673 75"},{"winner_name":"James Ward","loser_name":"Fritz Wolmarans","score":"64 63"},{"winner_name":"Austin Krajicek","loser_name":"Hiroki Moriya","score":"62 46 62"},{"winner_name":"Alex Bogomolov Jr.","loser_name":"Dennis Novikov","score":"63 62"},{"winner_name":"Ruben Bemelmans","loser_name":"Laurynas Grigelis","score":"63 63"},{"winner_name":"Chase Buchanan","loser_name":"Alexander Sarkissian","score":"26 64 63"},{"winner_name":"Andrea Collarini","loser_name":"Marcos Giron","score":"763 63"},{"winner_name":"Taro Daniel","loser_name":"Jordan Thompson","score":"766 674 64"},{"winner_name":"Rik De Voest","loser_name":"Jason Jung","score":"46 764 764"},{"winner_name":"Vincent Millot","loser_name":"James McGee","score":"64 64"},{"winner_name":"Yoshihito Nishioka","loser_name":"Fabrice Martin","score":"62 64"},{"winner_name":"Wayne Odesnik","loser_name":"Connor Smith","score":"63 767"}]},{"round":"3rd Round Qualifying","rowid":3,"data":[{"winner_name":"Jason Jung","loser_name":"Chris Wettengel","score":"75 62"},{"winner_name":"Fritz Wolmarans","loser_name":"Fabrice Martin","score":"62 765"},{"winner_name":"Connor Smith","loser_name":"Mitchell Krueger","score":"674 64 64"},{"winner_name":"Marcos Giron","loser_name":"Evan King","score":"63 765"}]},{"round":"2nd Round Qualifying","rowid":2,"data":[{"winner_name":"Jason Jung","loser_name":"Leon Frost","score":"64 60"},{"winner_name":"Fabrice Martin","loser_name":"Daniel Chu","score":"62 61"},{"winner_name":"Mitchell Krueger","loser_name":"George Jecminek","score":"64 64"},{"winner_name":"Evan King","loser_name":"Brayden Schnur","score":"64 36 62"},{"winner_name":"Marcos Giron","loser_name":"Clay Thompson","score":"61 62"},{"winner_name":"Fritz Wolmarans","loser_name":"Jordan Kerr","score":"61 64"},{"winner_name":"Connor Smith","loser_name":"Marcus Daniell","score":"76 63"},{"winner_name":"Chris Wettengel","loser_name":"Artem Sitak","score":"33 (RET)"}]},{"round":"1st Round Qualifying","rowid":1,"data":[{"winner_name":"Artem Sitak","loser_name":"Richard Gabb","score":"62 64"},{"winner_name":"Marcos Giron","loser_name":"Divij Sharan","score":"62 61"},{"winner_name":"Fritz Wolmarans","loser_name":"Benjamin Sigouin","score":"63 62"},{"winner_name":"Marcus Daniell","loser_name":"Alexander Day","score":"62 62"},{"winner_name":"Daniel Chu","loser_name":"Eric Fought","score":"62 60"},{"winner_name":"Leon Frost","loser_name":"Chris Hasek-Watt","score":"61 63"},{"winner_name":"George Jecminek","loser_name":"Bumpei Sato","score":"64 765"},{"winner_name":"Jordan Kerr","loser_name":"Kyryll Kryvchun","score":"62 60"},{"winner_name":"Brayden Schnur","loser_name":"Mico Santiago","score":"63 61"},{"winner_name":"Connor Smith","loser_name":"Riaan Du Toit","score":"75 64"},{"winner_name":"Clay Thompson","loser_name":"Philip Bester","score":"63 75"},{"winner_name":"Chris Wettengel","loser_name":"Patrick Walker","score":"75 673 64"}]}]
