[{"round":"Finals","rowid":5,"data":[{"winner_name":"John Bromwich","loser_name":"Adrian Quist","score":"64 61 63"}]},{"round":"Semi-Finals","rowid":4,"data":[{"winner_name":"John Bromwich","loser_name":"Vivian Mcgrath","score":"60 63 64"},{"winner_name":"Adrian Quist","loser_name":"Jack Crawford","score":"61 75 64"}]},{"round":"Quarter-Finals","rowid":3,"data":[{"winner_name":"John Bromwich","loser_name":"Donald Turnbull","score":"75 61 60"},{"winner_name":"Adrian Quist","loser_name":"Lionel Brodie","score":"63 62 68 63"},{"winner_name":"Vivian Mcgrath","loser_name":"Harry Hopman","score":"62 46 64 63"},{"winner_name":"Jack Crawford","loser_name":"James Gilchrist","score":"46 64 26 63 64"}]},{"round":"Round of 16","rowid":2,"data":[{"winner_name":"John Bromwich","loser_name":"Colin Long","score":"63 62 86"},{"winner_name":"Adrian Quist","loser_name":"Dinny Pails","score":"62 64 63"},{"winner_name":"Harry Hopman","loser_name":"Edgar Moon","score":"62 61 61"},{"winner_name":"Jack Crawford","loser_name":"Reg Ewin","score":"62 61 62"},{"winner_name":"James Gilchrist","loser_name":"Leonard Schwartz","score":"62 63 63"},{"winner_name":"Vivian Mcgrath","loser_name":"Max Bonner","score":"63 36 61 64"},{"winner_name":"Donald Turnbull","loser_name":"W. Vaughan","score":"62 61 63"},{"winner_name":"Lionel Brodie","loser_name":"Oswald William Thoma Sidwell","score":"62 75 64"}]},{"round":"Round of 32","rowid":1,"data":[{"winner_name":"John Bromwich","loser_name":"Edward Anstee","score":"62 63 61"},{"winner_name":"Adrian Quist","loser_name":"G. Wilkinson","score":"86 61 63"},{"winner_name":"Harry Hopman","loser_name":"Charles Vickers-Willis","score":"61 61 61"},{"winner_name":"Jack Crawford","loser_name":"Arthur Liddle","score":"64 60 62"},{"winner_name":"Leonard Schwartz","loser_name":"J.F. Pyle","score":"62 60 61"},{"winner_name":"Vivian Mcgrath","loser_name":"George Holland","score":"62 63 64"},{"winner_name":"Donald Turnbull","loser_name":"H. Impey","score":"63 60 63"},{"winner_name":"Oswald William Thoma Sidwell","loser_name":"Jack Harper","score":"62 108 26 64"},{"winner_name":"Max Bonner","loser_name":"Patrick Callaghan","score":"62 63 63"},{"winner_name":"Lionel Brodie","loser_name":"Les Hancock","score":"61 62 61"},{"winner_name":"Reg Ewin","loser_name":"Roy Felan","score":"61 63 61"},{"winner_name":"James Gilchrist","loser_name":"Abel Kay","score":"57 46 60 62 63"},{"winner_name":"Colin Long","loser_name":"John Clemenger","score":"46 63 (RET)"},{"winner_name":"Edgar Moon","loser_name":"William Lean","score":"64 61 61"},{"winner_name":"Dinny Pails","loser_name":"Mervyn Weston","score":"61 75 75"},{"winner_name":"W. Vaughan","loser_name":"Norman Wasley","score":"64 36 63 810 63"}]}]
