[{"tourney_name":"Hong Kong","surface":"Hard","data":[{"round":"Round of 32","Date":"1973-10-29","data":[{"winner_name":"Anand Amritraj","loser_name":"Jeck Chu","score":"63 62"},{"winner_name":"Vijay Amritraj","loser_name":"Tau Luu","score":"62 62"},{"winner_name":"Mal Anderson","loser_name":"Alan Ho","score":"61 60"},{"winner_name":"Syd Ball","loser_name":"Eddie Cruz","score":"76 76"},{"winner_name":"John Bartlett","loser_name":"Zeljko Franulovic","score":"61 76"},{"winner_name":"John Cooper","loser_name":"Bob Giltinan","score":"76 67 60"},{"winner_name":"Paul Gerken","loser_name":"Alexander Marcial","score":"60 64"},{"winner_name":"Brian Gottfried","loser_name":"William Koo","score":"61 60"},{"winner_name":"Milan Holecek","loser_name":"Kenneth Tsui","score":"61 60"},{"winner_name":"Rod Laver","loser_name":"Dick Dell","score":"46 63 63"},{"winner_name":"Jim McManus","loser_name":"Osamu Ishiguro","score":"61 62"},{"winner_name":"Charlie Pasarell","loser_name":"Charles Chang","score":"64 62"},{"winner_name":"Raul Ramirez","loser_name":"Ashley Cooper","score":"64 46 61"},{"winner_name":"Jeff Simpson","loser_name":"Po Tau","score":"64 60"},{"winner_name":"Sherwood Stewart","loser_name":"Colin Dibley","score":"64 61"},{"winner_name":"Fred Stolle","loser_name":"K.S. Leung","score":"61 63"}]},{"round":"Round of 16","Date":"1973-10-30","data":[{"winner_name":"Anand Amritraj","loser_name":"Sherwood Stewart","score":"46 75 86"},{"winner_name":"Mal Anderson","loser_name":"Milan Holecek","score":"63 76"},{"winner_name":"Paul Gerken","loser_name":"Syd Ball","score":"36 76 119"},{"winner_name":"Brian Gottfried","loser_name":"Jeff Simpson","score":"64 61"},{"winner_name":"Rod Laver","loser_name":"John Cooper","score":"63 75"},{"winner_name":"Charlie Pasarell","loser_name":"Vijay Amritraj","score":"63 64"},{"winner_name":"Raul Ramirez","loser_name":"John Bartlett","score":"63 62"},{"winner_name":"Fred Stolle","loser_name":"Jim McManus","score":"62 63"}]},{"round":"Quarter-Finals","Date":"1973-10-31","data":[{"winner_name":"Anand Amritraj","loser_name":"Mal Anderson","score":"63 64"},{"winner_name":"Rod Laver","loser_name":"Paul Gerken","score":"76 62"},{"winner_name":"Charlie Pasarell","loser_name":"Raul Ramirez","score":"62 76"},{"winner_name":"Fred Stolle","loser_name":"Brian Gottfried","score":"63 64"}]},{"round":"Semi-Finals","Date":"1973-11-01","data":[{"winner_name":"Rod Laver","loser_name":"Anand Amritraj","score":"63 63"},{"winner_name":"Charlie Pasarell","loser_name":"Fred Stolle","score":"60 67 64"}]},{"round":"Final","Date":"1973-11-02","data":[{"winner_name":"Rod Laver","loser_name":"Charlie Pasarell","score":"63 36 62 62"}]}]}]
