[{"round":"Finals","rowid":5,"data":[{"winner_name":"Karsten Braasch","loser_name":"Markus Naewie","score":"62 36 62"}]},{"round":"Semi-Finals","rowid":4,"data":[{"winner_name":"Karsten Braasch","loser_name":"Martin Damm","score":"76 75"},{"winner_name":"Markus Naewie","loser_name":"Lionel Roux","score":"62 62"}]},{"round":"Quarter-Finals","rowid":3,"data":[{"winner_name":"Karsten Braasch","loser_name":"Thierry Guardiola","score":"61 61"},{"winner_name":"Markus Naewie","loser_name":"Luis Herrera","score":"36 63 64"},{"winner_name":"Martin Damm","loser_name":"Martin Strelba","score":"67 64 76"},{"winner_name":"Lionel Roux","loser_name":"Claudio Mezzadri","score":"67 63 64"}]},{"round":"Round of 16","rowid":2,"data":[{"winner_name":"Karsten Braasch","loser_name":"Francisco Montana","score":"26 60 76"},{"winner_name":"Markus Naewie","loser_name":"Sandon Stolle","score":"63 61"},{"winner_name":"Thierry Guardiola","loser_name":"Byron Black","score":"76 76"},{"winner_name":"Martin Strelba","loser_name":"Olivier Soules","score":"57 62 64"},{"winner_name":"Martin Damm","loser_name":"Chris Pridham","score":"36 62 76"},{"winner_name":"Luis Herrera","loser_name":"Gilad Bloom","score":"16 63 75"},{"winner_name":"Claudio Mezzadri","loser_name":"Tarik Benhabiles","score":"62 60"},{"winner_name":"Lionel Roux","loser_name":"Kenny Thorne","score":"64 62"}]},{"round":"Round of 32","rowid":1,"data":[{"winner_name":"Lionel Roux","loser_name":"Marcelo Filippini","score":"36 64 62"},{"winner_name":"Chris Pridham","loser_name":"Patrik Kuhnen","score":"64 64"},{"winner_name":"Karsten Braasch","loser_name":"Ettore Rossetti","score":"62 62"},{"winner_name":"Luis Herrera","loser_name":"Luiz Mattar","score":"76 75"},{"winner_name":"Markus Naewie","loser_name":"Henrik Holm","score":"76 76"},{"winner_name":"Byron Black","loser_name":"Marian Vajda","score":"62 75"},{"winner_name":"Martin Strelba","loser_name":"Eric Winogradsky","score":"62 61"},{"winner_name":"Claudio Mezzadri","loser_name":"Andrei Olhovskiy","score":"61 76"},{"winner_name":"Tarik Benhabiles","loser_name":"Guillermo Vilas","score":"64 63"},{"winner_name":"Gilad Bloom","loser_name":"Mansour Bahrami","score":"63 57 61"},{"winner_name":"Martin Damm","loser_name":"Arne Thoms","score":"63 62"},{"winner_name":"Thierry Guardiola","loser_name":"Peter Lundgren","score":"64 64"},{"winner_name":"Francisco Montana","loser_name":"Joao Cunha-Silva","score":"75 67 62"},{"winner_name":"Olivier Soules","loser_name":"Diego Perez","score":"63 46 61"},{"winner_name":"Sandon Stolle","loser_name":"Nuno Marques","score":"76 75"},{"winner_name":"Kenny Thorne","loser_name":"Christian Ruud","score":"62 63"}]}]
