[{"round":"Finals","rowid":8,"data":[{"winner_name":"Damir Dzumhur","loser_name":"Igor Sijsling","score":"61 26 61"}]},{"round":"Semi-Finals","rowid":7,"data":[{"winner_name":"Damir Dzumhur","loser_name":"Grega Zemlja","score":"75 763"},{"winner_name":"Igor Sijsling","loser_name":"Tristan Lamasine","score":"64 63"}]},{"round":"Quarter-Finals","rowid":6,"data":[{"winner_name":"Damir Dzumhur","loser_name":"Dennis Novak","score":"46 63 764"},{"winner_name":"Igor Sijsling","loser_name":"Victor Hanescu","score":"64 766"},{"winner_name":"Grega Zemlja","loser_name":"Tobias Kamke","score":"763 36 64"},{"winner_name":"Tristan Lamasine","loser_name":"Constant Lestienne","score":"26 762 63"}]},{"round":"Round of 16","rowid":5,"data":[{"winner_name":"Damir Dzumhur","loser_name":"Marcin Gawron","score":"64 62"},{"winner_name":"Constant Lestienne","loser_name":"Jan-Lennard Struff","score":"61 63"},{"winner_name":"Igor Sijsling","loser_name":"Tallon Griekspoor","score":"61 62"},{"winner_name":"Tobias Kamke","loser_name":"Eduardo Dischinger","score":"62 61"},{"winner_name":"Victor Hanescu","loser_name":"Calvin Hemery","score":"673 63 75"},{"winner_name":"Tristan Lamasine","loser_name":"Adrian Ungur","score":"36 75 61"},{"winner_name":"Dennis Novak","loser_name":"Maxime Chazal","score":"57 64 62"},{"winner_name":"Grega Zemlja","loser_name":"Julien Cagnina","score":"64 46 62"}]},{"round":"Round of 32","rowid":4,"data":[{"winner_name":"Damir Dzumhur","loser_name":"Marek Michalicka","score":"62 63"},{"winner_name":"Jan-Lennard Struff","loser_name":"Jesse Huta Galung","score":"769 64"},{"winner_name":"Grega Zemlja","loser_name":"Thiemo de Bakker","score":"63 64"},{"winner_name":"Igor Sijsling","loser_name":"Vadym Ursu","score":"62 60"},{"winner_name":"Tobias Kamke","loser_name":"Thomas Schoorel","score":"63 62"},{"winner_name":"Dennis Novak","loser_name":"Germain Gigounon","score":"60 62"},{"winner_name":"Calvin Hemery","loser_name":"Adrian Sikora","score":"764 64"},{"winner_name":"Tristan Lamasine","loser_name":"Romain Barbosa","score":"62 63"},{"winner_name":"Julien Cagnina","loser_name":"Jelle Sels","score":"764 768"},{"winner_name":"Maxime Chazal","loser_name":"Vladimir Ivanov","score":"63 75"},{"winner_name":"Eduardo Dischinger","loser_name":"Riccardo Bellotti","score":"64 763"},{"winner_name":"Marcin Gawron","loser_name":"Grzegorz Panfil","score":"61 64"},{"winner_name":"Tallon Griekspoor","loser_name":"Jules Marie","score":"60 63"},{"winner_name":"Victor Hanescu","loser_name":"Vincent Van den Honert","score":"61 64"},{"winner_name":"Constant Lestienne","loser_name":"Arthur De Greef","score":"46 765 61"},{"winner_name":"Adrian Ungur","loser_name":"Alexandar Lazov","score":"63 57 75"}]},{"round":"3rd Round Qualifying","rowid":3,"data":[{"winner_name":"Romain Barbosa","loser_name":"Roy De Valk","score":"62 764"},{"winner_name":"Marcin Gawron","loser_name":"Jerome Inzerillo","score":"62 61"},{"winner_name":"Eduardo Dischinger","loser_name":"Andrei Vasilevski","score":"46 63 764"},{"winner_name":"Vadym Ursu","loser_name":"Lennert Van Der Linden","score":"62 61"}]},{"round":"2nd Round Qualifying","rowid":2,"data":[{"winner_name":"Romain Barbosa","loser_name":"Bobbie De Goeijen","score":"61 62"},{"winner_name":"Vadym Ursu","loser_name":"Philipp Davydenko","score":"674 63 63"},{"winner_name":"Jerome Inzerillo","loser_name":"Colin Van Beem","score":"64 62"},{"winner_name":"Andrei Vasilevski","loser_name":"Leonardo Kirche","score":"46 64 64"},{"winner_name":"Roy De Valk","loser_name":"Niels Lootsma","score":"60 60"},{"winner_name":"Marcin Gawron","loser_name":"Kevin Kylar","score":"61 60"},{"winner_name":"Eduardo Dischinger","loser_name":"Ivo Mijic","score":"(W/O)"},{"winner_name":"Lennert Van Der Linden","loser_name":"Sander Arends","score":"75 62"}]},{"round":"1st Round Qualifying","rowid":1,"data":[{"winner_name":"Sander Arends","loser_name":"Sebastian Rivera","score":"(W/O)"},{"winner_name":"Bobbie De Goeijen","loser_name":"Jasper van Vliet","score":"60 63"},{"winner_name":"Andrei Vasilevski","loser_name":"Tomasz Bednarek","score":"64 60"}]}]
