[{"round":"Final","rowid":7,"data":[{"winner_name":"Emil Ruusuvuori","loser_name":"Roberto Cid Subervi","score":"63 62"}]},{"round":"Semifinals","rowid":6,"data":[{"winner_name":"Roberto Cid Subervi","loser_name":"Cem Ilkel","score":"26 61 765"},{"winner_name":"Emil Ruusuvuori","loser_name":"Khumoyun Sultanov","score":"762 46 761"}]},{"round":"Quarterfinals","rowid":5,"data":[{"winner_name":"Roberto Cid Subervi","loser_name":"Gleb Sakharov","score":"63 63"},{"winner_name":"Cem Ilkel","loser_name":"Aleksandar Vukic","score":"63 64"},{"winner_name":"Emil Ruusuvuori","loser_name":"Pavel Kotov","score":"75 40 (RET)"},{"winner_name":"Khumoyun Sultanov","loser_name":"Evan King","score":"75 61"}]},{"round":"Round of 16","rowid":4,"data":[{"winner_name":"Gleb Sakharov","loser_name":"Di Wu","score":"63 764"},{"winner_name":"Cem Ilkel","loser_name":"Aldin Setkic","score":"36 63 64"},{"winner_name":"Evan King","loser_name":"Marcelo Tomas Barrios Vera","score":"63 75"},{"winner_name":"Pavel Kotov","loser_name":"Ivan Gakhov","score":"64 46 64"},{"winner_name":"Aleksandar Vukic","loser_name":"Tsung-Hua Yang","score":"75 62"},{"winner_name":"Roberto Cid Subervi","loser_name":"Altug Celikbilek","score":"75 16 62"},{"winner_name":"Khumoyun Sultanov","loser_name":"Baptiste Crepatte","score":"63 36 61"},{"winner_name":"Emil Ruusuvuori","loser_name":"Edan Leshem","score":"63 62"}]},{"round":"Round of 32","rowid":3,"data":[{"winner_name":"Emil Ruusuvuori","loser_name":"Pedja Krstin","score":"46 64 60"},{"winner_name":"Gleb Sakharov","loser_name":"Maximilian Neuchrist","score":"767 75"},{"winner_name":"Khumoyun Sultanov","loser_name":"Marc-Andrea Huesler","score":"63 63"},{"winner_name":"Cem Ilkel","loser_name":"Sebastian Korda","score":"765 6710 63"},{"winner_name":"Altug Celikbilek","loser_name":"Sasi Kumar Mukund","score":"36 762 62"},{"winner_name":"Marcelo Tomas Barrios Vera","loser_name":"Shuichi Sekiguchi","score":"(W/O)"},{"winner_name":"Pavel Kotov","loser_name":"Sidharth Rawat","score":"64 63"},{"winner_name":"Tsung-Hua Yang","loser_name":"Teymuraz Gabashvili","score":"62 62"},{"winner_name":"Ivan Gakhov","loser_name":"Denis Yevseyev","score":"64 769"},{"winner_name":"Aleksandar Vukic","loser_name":"Sanjar Fayziev","score":"64 36 63"},{"winner_name":"Evan King","loser_name":"Olimjon Nabiev","score":"62 61"},{"winner_name":"Roberto Cid Subervi","loser_name":"Andres Artunedo Martinavarro","score":"62 64"},{"winner_name":"Aldin Setkic","loser_name":"Saida'Lo Saidkarimov","score":"62 63"},{"winner_name":"Baptiste Crepatte","loser_name":"Konstantin Kravchuk","score":"46 63 64"},{"winner_name":"Edan Leshem","loser_name":"Alejandro Tabilo","score":"64 64"},{"winner_name":"Di Wu","loser_name":"Alexander Zhurbin","score":"60 764"}]},{"round":"Round of 64","rowid":2,"data":[{"winner_name":"Andres Artunedo Martinavarro","loser_name":"Renta Tokuda","score":"57 767 60"},{"winner_name":"Altug Celikbilek","loser_name":"N Vijay Sundar Prashanth","score":"63 64"},{"winner_name":"Sanjar Fayziev","loser_name":"Anton Chekhov","score":"60 63"},{"winner_name":"Teymuraz Gabashvili","loser_name":"Ibrokhimjon Urinov","score":"63 63"},{"winner_name":"Ivan Gakhov","loser_name":"Shonigmatjon Shofayziyev","score":"64 62"},{"winner_name":"Sebastian Korda","loser_name":"Timur Khabibulin","score":"62 62"},{"winner_name":"Konstantin Kravchuk","loser_name":"Timur Sottimov","score":"62 62"},{"winner_name":"Edan Leshem","loser_name":"Andrey Golubev","score":"61 64"},{"winner_name":"Olimjon Nabiev","loser_name":"Ivan Nedelko","score":"46 764 03 (RET)"},{"winner_name":"Maximilian Neuchrist","loser_name":"Alexey Zakharov","score":"765 63"},{"winner_name":"Sidharth Rawat","loser_name":"Vladyslav Manafov","score":"762 62"},{"winner_name":"Emil Ruusuvuori","loser_name":"Dimitriy Voronin","score":"61 61"},{"winner_name":"Saida'Lo Saidkarimov","loser_name":"Karim-Mohamed Maamoun","score":"64 21 (RET)"},{"winner_name":"Shuichi Sekiguchi","loser_name":"Makoto Ochi","score":"64 64"},{"winner_name":"Khumoyun Sultanov","loser_name":"Arjun Kadhe","score":"62 64"},{"winner_name":"Alexander Zhurbin","loser_name":"Sergey Fomin","score":"57 64 62"}]},{"round":"1st Round Qualifying","rowid":1,"data":[{"winner_name":"Timur Khabibulin","loser_name":"Adil Karimov","score":"768 61"},{"winner_name":"Alexey Zakharov","loser_name":"Michail Pervolarakis","score":"61 36 61"}]}]
