[{"round":"Finals","rowid":8,"data":[{"winner_name":"Alex Kuznetsov","loser_name":"Wayne Odesnik","score":"60 62"}]},{"round":"Semi-Finals","rowid":7,"data":[{"winner_name":"Wayne Odesnik","loser_name":"Denys Molchanov","score":"761 671 61"},{"winner_name":"Alex Kuznetsov","loser_name":"Somdev Devvarman","score":"36 61 63"}]},{"round":"Quarter-Finals","rowid":6,"data":[{"winner_name":"Denys Molchanov","loser_name":"Guido Pella","score":"764 46 75"},{"winner_name":"Wayne Odesnik","loser_name":"Facundo Arguello","score":"63 60"},{"winner_name":"Somdev Devvarman","loser_name":"Mischa Zverev","score":"64 62"},{"winner_name":"Alex Kuznetsov","loser_name":"Steve Johnson","score":"62 36 61"}]},{"round":"Round of 16","rowid":5,"data":[{"winner_name":"Guido Pella","loser_name":"Ze Zhang","score":"64 26 61"},{"winner_name":"Wayne Odesnik","loser_name":"Cedrik-Marcel Stebe","score":"63 36 64"},{"winner_name":"Facundo Arguello","loser_name":"Teymuraz Gabashvili","score":"62 61"},{"winner_name":"Somdev Devvarman","loser_name":"Ilija Bozoljac","score":"64 64"},{"winner_name":"Steve Johnson","loser_name":"Rhyne Williams","score":"61 63"},{"winner_name":"Alex Kuznetsov","loser_name":"Tim Smyczek","score":"36 761 64"},{"winner_name":"Denys Molchanov","loser_name":"Frank Dancevic","score":"75 762"},{"winner_name":"Mischa Zverev","loser_name":"James Ward","score":"61 26 64"}]},{"round":"Round of 32","rowid":4,"data":[{"winner_name":"Mischa Zverev","loser_name":"Michael Russell","score":"60 63"},{"winner_name":"Facundo Arguello","loser_name":"Ryan Harrison","score":"763 64"},{"winner_name":"Frank Dancevic","loser_name":"Martin Alund","score":"63 62"},{"winner_name":"Alex Kuznetsov","loser_name":"Benjamin Becker","score":"62 62"},{"winner_name":"Somdev Devvarman","loser_name":"Jesse Levine","score":"674 63 64"},{"winner_name":"Guido Pella","loser_name":"Bradley Klahn","score":"675 762 62"},{"winner_name":"Steve Johnson","loser_name":"Jack Sock","score":"767 22 (RET)"},{"winner_name":"Wayne Odesnik","loser_name":"Alex Bogomolov Jr.","score":"61 61"},{"winner_name":"Ilija Bozoljac","loser_name":"Yong-Kyu Lim","score":"63 46 64"},{"winner_name":"Teymuraz Gabashvili","loser_name":"Mitchell Frank","score":"63 62"},{"winner_name":"Denys Molchanov","loser_name":"Ivo Karlovic","score":"64 36 61"},{"winner_name":"Tim Smyczek","loser_name":"Bjorn Fratangelo","score":"36 64 64"},{"winner_name":"Cedrik-Marcel Stebe","loser_name":"Adrian Menendez-Maceiras","score":"61 63"},{"winner_name":"James Ward","loser_name":"Kyle Edmund","score":"63 64"},{"winner_name":"Rhyne Williams","loser_name":"Tennys Sandgren","score":"62 63"},{"winner_name":"Ze Zhang","loser_name":"Suk-Young Jeong","score":"62 62"}]},{"round":"3rd Round Qualifying","rowid":3,"data":[{"winner_name":"Alex Kuznetsov","loser_name":"Mitchell Krueger","score":"63 63"},{"winner_name":"Suk-Young Jeong","loser_name":"Marek Michalicka","score":"763 63"},{"winner_name":"Ilija Bozoljac","loser_name":"Fritz Wolmarans","score":"75 64"},{"winner_name":"Yong-Kyu Lim","loser_name":"Jason Jung","score":"75 674 62"}]},{"round":"2nd Round Qualifying","rowid":2,"data":[{"winner_name":"Jason Jung","loser_name":"Denys Molchanov","score":""},{"winner_name":"Alex Kuznetsov","loser_name":"Roman Borvanov","score":"62 62"},{"winner_name":"Suk-Young Jeong","loser_name":"Yoshihito Nishioka","score":"60 64"},{"winner_name":"Ilija Bozoljac","loser_name":"Reid Carleton","score":"763 61"},{"winner_name":"Fritz Wolmarans","loser_name":"Jeff Dadamo","score":"62 763"},{"winner_name":"Marek Michalicka","loser_name":"Mark Oljaca","score":"62 62"},{"winner_name":"Yong-Kyu Lim","loser_name":"Terrell Celestine","score":"64 61"},{"winner_name":"Mitchell Krueger","loser_name":"Thai-Son Kwiatkowski","score":"36 63 62"}]},{"round":"1st Round Qualifying","rowid":1,"data":[{"winner_name":"Mitchell Krueger","loser_name":"Michael Venus","score":"26 75 62"},{"winner_name":"Yong-Kyu Lim","loser_name":"Julien Link","score":"62 10 (RET)"},{"winner_name":"Roman Borvanov","loser_name":"Luka Gregorc","score":"36 75 63"},{"winner_name":"Reid Carleton","loser_name":"Naoki Nakagawa","score":"765 63"},{"winner_name":"Terrell Celestine","loser_name":"Jhonatan Gonzalez","score":"62 62"},{"winner_name":"Jeff Dadamo","loser_name":"Vladimir Obradovic","score":"62 62"},{"winner_name":"Jason Jung","loser_name":"Mohd Assri Merzuki","score":"62 61"},{"winner_name":"Thai-Son Kwiatkowski","loser_name":"Takanyi Garanganga","score":"674 60 60"},{"winner_name":"Yoshihito Nishioka","loser_name":"Harris Trismen","score":"60 61"},{"winner_name":"Mark Oljaca","loser_name":"Francis Williams","score":"62 61"}]}]
