[{"round":"Finals","rowid":8,"data":[{"winner_name":"Santiago Giraldo","loser_name":"Michael Russell","score":"63 62"}]},{"round":"Semi-Finals","rowid":7,"data":[{"winner_name":"Michael Russell","loser_name":"Leonardo Mayer","score":"75 63"},{"winner_name":"Santiago Giraldo","loser_name":"Carlos Berlocq","score":"62 62"}]},{"round":"Quarter-Finals","rowid":6,"data":[{"winner_name":"Leonardo Mayer","loser_name":"Ramon Delgado","score":"(W/O)"},{"winner_name":"Michael Russell","loser_name":"Benjamin Becker","score":"63 46 62"},{"winner_name":"Santiago Giraldo","loser_name":"Alejandro Falla","score":"75 64"},{"winner_name":"Carlos Berlocq","loser_name":"Izak Van der Merwe","score":"7610 63"}]},{"round":"Round of 16","rowid":5,"data":[{"winner_name":"Leonardo Mayer","loser_name":"Bruno Echagaray","score":"61 766"},{"winner_name":"Carlos Berlocq","loser_name":"Thiago Alves","score":"63 60"},{"winner_name":"Benjamin Becker","loser_name":"Ivan Miranda","score":"763 64"},{"winner_name":"Ramon Delgado","loser_name":"Kristian Pless","score":"63 64"},{"winner_name":"Santiago Giraldo","loser_name":"Todd Widom","score":"61 767"},{"winner_name":"Alejandro Falla","loser_name":"Joao Souza","score":"63 763"},{"winner_name":"Michael Russell","loser_name":"Horacio Zeballos","score":"62 61"},{"winner_name":"Izak Van der Merwe","loser_name":"Maximo Gonzalez","score":"63 60"}]},{"round":"Round of 32","rowid":4,"data":[{"winner_name":"Leonardo Mayer","loser_name":"Julio Cesar Campozano","score":"62 62"},{"winner_name":"Thiago Alves","loser_name":"Rogerio Dutra Silva","score":"63 64"},{"winner_name":"Benjamin Becker","loser_name":"Ricardo Mello","score":"62 64"},{"winner_name":"Alejandro Falla","loser_name":"Pablo Cuevas","score":"63 75"},{"winner_name":"Kristian Pless","loser_name":"Carlos Salamanca","score":"64 62"},{"winner_name":"Santiago Giraldo","loser_name":"Daniel Dutra da Silva","score":"62 75"},{"winner_name":"Michael Russell","loser_name":"Ricardo Hocevar","score":"36 63 62"},{"winner_name":"Izak Van der Merwe","loser_name":"Juan Pablo Brzezicki","score":"64 36 64"},{"winner_name":"Carlos Berlocq","loser_name":"Andre Miele","score":"46 63 62"},{"winner_name":"Ramon Delgado","loser_name":"Caio Zampieri","score":"62 63"},{"winner_name":"Bruno Echagaray","loser_name":"Harel Levy","score":"62 75"},{"winner_name":"Maximo Gonzalez","loser_name":"Fernando Vicente","score":"63 36 63"},{"winner_name":"Ivan Miranda","loser_name":"Eric Nunez","score":"64 62"},{"winner_name":"Joao Souza","loser_name":"Alejo Apud","score":"46 62 61"},{"winner_name":"Todd Widom","loser_name":"Carlos Avellan","score":"64 63"},{"winner_name":"Horacio Zeballos","loser_name":"Marcel Felder","score":"64 62"}]},{"round":"3rd Round Qualifying","rowid":3,"data":[{"winner_name":"Maximo Gonzalez","loser_name":"Patricio Alvarado","score":"75 62"},{"winner_name":"Daniel Dutra da Silva","loser_name":"Marcin Gawron","score":"678 64 764"},{"winner_name":"Izak Van der Merwe","loser_name":"Alejandro Gonzalez","score":"60 64"},{"winner_name":"Carlos Salamanca","loser_name":"Adam Vejmelka","score":"62 765"}]},{"round":"2nd Round Qualifying","rowid":2,"data":[{"winner_name":"Maximo Gonzalez","loser_name":"Sat Galan","score":"62 46 61"},{"winner_name":"Daniel Dutra da Silva","loser_name":"Stephen Bass","score":"64 61"},{"winner_name":"Izak Van der Merwe","loser_name":"Brian Battistone","score":"63 62"},{"winner_name":"Carlos Salamanca","loser_name":"Filip Krajinovic","score":"64 63"},{"winner_name":"Patricio Alvarado","loser_name":"Ivan Endara","score":"26 60 61"},{"winner_name":"Marcin Gawron","loser_name":"Andres Arango","score":"62 677 60"},{"winner_name":"Alejandro Gonzalez","loser_name":"Federico Torresi","score":"46 63 61"},{"winner_name":"Adam Vejmelka","loser_name":"Adrians Zguns","score":"63 763"}]},{"round":"1st Round Qualifying","rowid":1,"data":[{"winner_name":"Maximo Gonzalez","loser_name":"Juan-Xavier Ponce","score":"64 60"},{"winner_name":"Daniel Dutra da Silva","loser_name":"David Orces","score":"60 61"},{"winner_name":"Izak Van der Merwe","loser_name":"Guillermo Lasso","score":"60 61"},{"winner_name":"Adam Vejmelka","loser_name":"Juan Sebastian Cabal","score":"63 62"},{"winner_name":"Carlos Salamanca","loser_name":"Justin O'Neal","score":"75 63"},{"winner_name":"Alejandro Gonzalez","loser_name":"Enrico Burzi","score":"60 61"},{"winner_name":"Marcin Gawron","loser_name":"Frederic Niemeyer","score":"(W/O)"},{"winner_name":"Patricio Alvarado","loser_name":"Alex Kuznetsov","score":"763 46 62"},{"winner_name":"Andres Arango","loser_name":"Robert Wright","score":"36 63 75"},{"winner_name":"Stephen Bass","loser_name":"Jorge Montoya","score":"62 61"},{"winner_name":"Brian Battistone","loser_name":"Hector Sanabria","score":"761 60"},{"winner_name":"Ivan Endara","loser_name":"Jorge Barreda","score":"60 63"},{"winner_name":"Sat Galan","loser_name":"Juan Bolona","score":"61 62"},{"winner_name":"Filip Krajinovic","loser_name":"Chris Klingemann","score":"36 760 63"},{"winner_name":"Federico Torresi","loser_name":"Gastao Elias","score":"64 64"},{"winner_name":"Adrians Zguns","loser_name":"Diego Acosta","score":"61 61"}]}]
