[{"tourney_name":"Wimbledon","surface":"Grass","data":[{"round":"1st Round Qualifying","Date":"2008-06-23","data":[{"winner_name":"Gilles Muller","loser_name":"Marsel Ilhan","score":"677 64 64"},{"winner_name":"Christophe Rochus","loser_name":"Mikhail Elgin","score":"64 63"},{"winner_name":"Fred Gil","loser_name":"Dominik Meffert","score":"64 36 64"},{"winner_name":"Philipp Petzschner","loser_name":"Morgan Phillips","score":"62 42 (RET)"},{"winner_name":"Robert Kendrick","loser_name":"Peter Polansky","score":"64 62"},{"winner_name":"Go Soeda","loser_name":"Francesco Aldi","score":"64 64"},{"winner_name":"Kristian Pless","loser_name":"Gary Lugassy","score":"674 765 63"},{"winner_name":"Paul Capdeville","loser_name":"Francesco Piccari","score":"36 62 63"},{"winner_name":"Flavio Cipolla","loser_name":"Joao Souza","score":"63 60"},{"winner_name":"Robert Smeets","loser_name":"Amer Delic","score":"63 675 63"},{"winner_name":"Alexander Peya","loser_name":"Sam Warburg","score":"62 64"},{"winner_name":"Bjorn Rehnquist","loser_name":"Ivan Navarro","score":"764 63"},{"winner_name":"Sergiy Stakhovsky","loser_name":"Todd Widom","score":"62 63"},{"winner_name":"Stephane Bohli","loser_name":"Lukasz Kubot","score":"64 60"},{"winner_name":"Chris Eaton","loser_name":"Mikhail Kukushkin","score":"26 64 75"},{"winner_name":"Rik De Voest","loser_name":"Dick Norman","score":"36 64 61"},{"winner_name":"Jan Hernych","loser_name":"Andrew Coelho","score":"64 763"},{"winner_name":"Jesse Levine","loser_name":"Irakli Labadze","score":"62 63"},{"winner_name":"Andreas Beck","loser_name":"Paolo Lorenzi","score":"61 675 63"},{"winner_name":"Thomas Oger","loser_name":"Alun Jones","score":"60 60"},{"winner_name":"Andrey Golubev","loser_name":"Jean-Christophe Faurel","score":"765 64"},{"winner_name":"Aisam-Ul-Haq Qureshi","loser_name":"Josselin Ouanna","score":"765 63"},{"winner_name":"Edouard Roger-Vasselin","loser_name":"Augustin Gensse","score":"62 60"},{"winner_name":"Adrian Cruciat","loser_name":"Gabriel Trujillo-Soler","score":"61 21 (RET)"},{"winner_name":"Santiago Gonzalez","loser_name":"Leonardo Mayer","score":"63 765"},{"winner_name":"Olivier Patience","loser_name":"Jesse Witten","score":"676 62 1311"},{"winner_name":"Frederic Niemeyer","loser_name":"Harel Levy","score":"62 75"},{"winner_name":"Pavel Snobel","loser_name":"Dusan Vemic","score":"75 46 108"},{"winner_name":"Alex Bogomolov Jr.","loser_name":"Joseph Sirianni","score":"766 763"},{"winner_name":"Hugo Armando","loser_name":"Mikhail Ledovskikh","score":"63 64"},{"winner_name":"Martin Fischer","loser_name":"Conor Niland","score":"671 64 64"},{"winner_name":"Simon Stadler","loser_name":"Daniel Cox","score":"62 62"},{"winner_name":"Prakash Amritraj","loser_name":"Jean-Rene Lisnard","score":"62 764"},{"winner_name":"Matthias Bachinger","loser_name":"Michael Lammer","score":"46 63 63"},{"winner_name":"Richard Bloomfield","loser_name":"Rui Machado","score":"63 75"},{"winner_name":"Ilija Bozoljac","loser_name":"Nicholas Monroe","score":"60 62"},{"winner_name":"Daniel Brands","loser_name":"Cristian Villagran","score":"63 64"},{"winner_name":"Pavel Chekhov","loser_name":"Adrian Mannarino","score":"36 32 (RET)"},{"winner_name":"Ti Chen","loser_name":"Alex Kuznetsov","score":"62 36 63"},{"winner_name":"Lukas Dlouhy","loser_name":"Woong-Sun Jun","score":"64 765"},{"winner_name":"Antony Dupuis","loser_name":"Adam Feeney","score":"62 75"},{"winner_name":"Rainer Eitzinger","loser_name":"Jan Mertl","score":"57 62 61"},{"winner_name":"Brendan Evans","loser_name":"Marc Fornell-Mestres","score":"62 62"},{"winner_name":"Alberto Francis","loser_name":"Filip Prpic","score":"63 63"},{"winner_name":"Stefano Galvani","loser_name":"Jimmy Wang","score":"61 62"},{"winner_name":"Josh Goodall","loser_name":"Ivo Klec","score":"64 63"},{"winner_name":"Tobias Kamke","loser_name":"Danai Udomchoke","score":"63 64"},{"winner_name":"Kevin Kim","loser_name":"Jonathan Marray","score":"64 75"},{"winner_name":"Alexander Kudryavtsev","loser_name":"Marc Lopez","score":"75 64"},{"winner_name":"David Marrero","loser_name":"Tomas Zib","score":"46 75 63"},{"winner_name":"Ricardo Mello","loser_name":"Adrian Menendez-Maceiras","score":"62 60"},{"winner_name":"Jan Minar","loser_name":"KJ Hippensteel","score":"64 46 60"},{"winner_name":"Max Mirnyi","loser_name":"Karol Beck","score":"64 64"},{"winner_name":"Wesley Moodie","loser_name":"Sebastien De Chaunac","score":"64 75"},{"winner_name":"Noam Okun","loser_name":"Ken Skupski","score":"64 62"},{"winner_name":"Dawid Olejniczak","loser_name":"Lukas Rosol","score":"766 64"},{"winner_name":"Jaroslav Pospisil","loser_name":"Fernando Vicente","score":"63 764"},{"winner_name":"Michal Przysiezny","loser_name":"Rajeev Ram","score":"763 767"},{"winner_name":"Martin Slanar","loser_name":"Juan-Martin Aranguren","score":"63 62"},{"winner_name":"Louk Sorensen","loser_name":"Edward Seator","score":"62 61"},{"winner_name":"Ryan Sweeting","loser_name":"Scoville Jenkins","score":"36 763 75"},{"winner_name":"Nicolas Todero","loser_name":"George Bastl","score":"64 64"},{"winner_name":"Jan Vacek","loser_name":"Colin Ebelthite","score":"64 64"},{"winner_name":"Izak Van der Merwe","loser_name":"Miguel Angel Lopez Jaen","score":"63 61"}]},{"round":"2nd Round Qualifying","Date":"2008-06-24","data":[{"winner_name":"Jaroslav Pospisil","loser_name":"Gilles Muller","score":"7610 763"},{"winner_name":"Christophe Rochus","loser_name":"Ryan Sweeting","score":"63 64"},{"winner_name":"Fred Gil","loser_name":"Noam Okun","score":"61 63"},{"winner_name":"Philipp Petzschner","loser_name":"Daniel Brands","score":"36 64 61"},{"winner_name":"Robert Kendrick","loser_name":"Josh Goodall","score":"64 64"},{"winner_name":"Michal Przysiezny","loser_name":"Go Soeda","score":"46 64 108"},{"winner_name":"Izak Van der Merwe","loser_name":"Kristian Pless","score":"75 768"},{"winner_name":"Alexander Kudryavtsev","loser_name":"Paul Capdeville","score":"765 46 86"},{"winner_name":"Flavio Cipolla","loser_name":"Max Mirnyi","score":"765 63"},{"winner_name":"Sergiy Stakhovsky","loser_name":"Prakash Amritraj","score":"63 16 63"},{"winner_name":"Nicolas Todero","loser_name":"Stephane Bohli","score":"673 75 62"},{"winner_name":"Rik De Voest","loser_name":"Jan Vacek","score":"62 36 97"},{"winner_name":"Jan Hernych","loser_name":"Ti Chen","score":"63 61"},{"winner_name":"Jesse Levine","loser_name":"Pavel Chekhov","score":"63 678 119"},{"winner_name":"Andreas Beck","loser_name":"Brendan Evans","score":"63 46 64"},{"winner_name":"Stefano Galvani","loser_name":"Andrey Golubev","score":"75 62"},{"winner_name":"Dawid Olejniczak","loser_name":"Aisam-Ul-Haq Qureshi","score":"769 63"},{"winner_name":"Edouard Roger-Vasselin","loser_name":"Louk Sorensen","score":"674 63 31 (RET)"},{"winner_name":"Adrian Cruciat","loser_name":"Martin Slanar","score":"62 75"},{"winner_name":"Olivier Patience","loser_name":"Matthias Bachinger","score":"765 674 63"},{"winner_name":"Simon Stadler","loser_name":"Rainer Eitzinger","score":"57 61 62"},{"winner_name":"Hugo Armando","loser_name":"Wesley Moodie","score":"26 765 64"},{"winner_name":"Richard Bloomfield","loser_name":"Thomas Oger","score":"62 60"},{"winner_name":"Ilija Bozoljac","loser_name":"Robert Smeets","score":"36 762 63"},{"winner_name":"Chris Eaton","loser_name":"Jan Minar","score":"6710 63 64"},{"winner_name":"Martin Fischer","loser_name":"Ricardo Mello","score":"75 57 64"},{"winner_name":"Santiago Gonzalez","loser_name":"David Marrero","score":"64 46 64"},{"winner_name":"Tobias Kamke","loser_name":"Bjorn Rehnquist","score":"767 61"},{"winner_name":"Kevin Kim","loser_name":"Alex Bogomolov Jr.","score":"64 765"},{"winner_name":"Frederic Niemeyer","loser_name":"Lukas Dlouhy","score":"63 63"},{"winner_name":"Alexander Peya","loser_name":"Alberto Francis","score":"63 36 62"},{"winner_name":"Pavel Snobel","loser_name":"Antony Dupuis","score":"63 64"}]},{"round":"3rd Round Qualifying","Date":"2008-06-25","data":[{"winner_name":"Christophe Rochus","loser_name":"Martin Fischer","score":"61 63 64"},{"winner_name":"Fred Gil","loser_name":"Hugo Armando","score":"62 765 46 763"},{"winner_name":"Philipp Petzschner","loser_name":"Adrian Cruciat","score":"64 57 57 62 63"},{"winner_name":"Kevin Kim","loser_name":"Robert Kendrick","score":"36 63 64 64"},{"winner_name":"Pavel Snobel","loser_name":"Flavio Cipolla","score":"60 64 63"},{"winner_name":"Sergiy Stakhovsky","loser_name":"Santiago Gonzalez","score":"63 64 75"},{"winner_name":"Dawid Olejniczak","loser_name":"Rik De Voest","score":"64 64 671 26 86"},{"winner_name":"Jan Hernych","loser_name":"Tobias Kamke","score":"63 764 762"},{"winner_name":"Jesse Levine","loser_name":"Alexander Kudryavtsev","score":"64 63 64"},{"winner_name":"Andreas Beck","loser_name":"Jaroslav Pospisil","score":"63 61 75"},{"winner_name":"Edouard Roger-Vasselin","loser_name":"Michal Przysiezny","score":"62 61 61"},{"winner_name":"Chris Eaton","loser_name":"Olivier Patience","score":"765 63 763"},{"winner_name":"Simon Stadler","loser_name":"Nicolas Todero","score":"6710 765 36 61 61"},{"winner_name":"Stefano Galvani","loser_name":"Ilija Bozoljac","score":"36 60 61 26 64"},{"winner_name":"Alexander Peya","loser_name":"Richard Bloomfield","score":"64 64 36 16 86"},{"winner_name":"Izak Van der Merwe","loser_name":"Frederic Niemeyer","score":"63 63 16 63"}]},{"round":"Round of 128","Date":"2008-06-26","data":[{"winner_name":"Roger Federer","loser_name":"Dominik Hrbaty","score":"63 62 62"},{"winner_name":"Rafael Nadal","loser_name":"Andreas Beck","score":"64 64 760"},{"winner_name":"Novak Djokovic","loser_name":"Michael Berrer","score":"75 26 63 60"},{"winner_name":"Benjamin Becker","loser_name":"Nikolay Davydenko","score":"64 64 64"},{"winner_name":"David Ferrer","loser_name":"Sergiy Stakhovsky","score":"766 63 13 (RET)"},{"winner_name":"Andy Roddick","loser_name":"Eduardo Schwank","score":"75 64 76"},{"winner_name":"Frank Dancevic","loser_name":"David Nalbandian","score":"64 62 64"},{"winner_name":"James Blake","loser_name":"Christophe Rochus","score":"36 63 61 64"},{"winner_name":"Richard Gasquet","loser_name":"Mardy Fish","score":"63 64 62"},{"winner_name":"Stan Wawrinka","loser_name":"Marcos Daniel","score":"63 62 75"},{"winner_name":"Andy Murray","loser_name":"Fabrice Santoro","score":"63 64 765"},{"winner_name":"Nicolas Almagro","loser_name":"Marcel Granollers","score":"46 63 75 62"},{"winner_name":"Fernando Gonzalez","loser_name":"Robby Ginepri","score":"763 75 75"},{"winner_name":"Radek Stepanek","loser_name":"Jan Hernych","score":"63 75 60"},{"winner_name":"Paul-Henri Mathieu","loser_name":"Oscar Hernandez","score":"36 62 60 62"},{"winner_name":"Mikhail Youzhny","loser_name":"Sergio Roitman","score":"61 64 60"},{"winner_name":"Tommy Robredo","loser_name":"Kristof Vliegen","score":"61 63 674 64"},{"winner_name":"Tomas Berdych","loser_name":"Evgeny Korolev","score":"46 61 64 36 75"},{"winner_name":"Fernando Verdasco","loser_name":"Philipp Kohlschreiber","score":"64 63 62"},{"winner_name":"Simon Stadler","loser_name":"Ivo Karlovic","score":"46 764 63 75"},{"winner_name":"Juan Carlos Ferrero","loser_name":"Sam Querrey","score":"26 64 64 64"},{"winner_name":"Marcos Baghdatis","loser_name":"Steve Darcis","score":"63 62 675 63"},{"winner_name":"Jurgen Melzer","loser_name":"Ivan Ljubicic","score":"64 767 46 26 63"},{"winner_name":"Lleyton Hewitt","loser_name":"Robin Haase","score":"674 63 63 671 62"},{"winner_name":"Jarkko Nieminen","loser_name":"Wayne Odesnik","score":"63 (RET)"},{"winner_name":"Gilles Simon","loser_name":"Dawid Olejniczak","score":"63 64 62"},{"winner_name":"Andreas Seppi","loser_name":"Tobias Kamke","score":"57 63 62 64"},{"winner_name":"Dmitry Tursunov","loser_name":"Nicolas Mahut","score":"64 678 767 36 75"},{"winner_name":"Nicolas Kiefer","loser_name":"Julien Benneteau","score":"61 75 63"},{"winner_name":"Mario Ancic","loser_name":"Michael Llodra","score":"64 767 20 (RET)"},{"winner_name":"Feliciano Lopez","loser_name":"Brian Dabul","score":"761 36 63 64"},{"winner_name":"Igor Andreev","loser_name":"Jiri Vanek","score":"676 762 62 62"},{"winner_name":"Thomaz Bellucci","loser_name":"Igor Kunitsyn","score":"765 765 36 62"},{"winner_name":"Simone Bolelli","loser_name":"Alex Bogdanovic","score":"764 46 63 764"},{"winner_name":"Ilija Bozoljac","loser_name":"Chris Guccione","score":"36 64 64 63"},{"winner_name":"Agustin Calleri","loser_name":"Kevin Anderson","score":"46 75 75 61"},{"winner_name":"Jeremy Chardy","loser_name":"Fred Gil","score":"75 671 46 64 63"},{"winner_name":"Marin Cilic","loser_name":"Edouard Roger-Vasselin","score":"64 63 764"},{"winner_name":"Arnaud Clement","loser_name":"Jonas Bjorkman","score":"46 762 64 764"},{"winner_name":"Juan Martin del Potro","loser_name":"Pavel Snobel","score":"64 62 63"},{"winner_name":"Chris Eaton","loser_name":"Boris Pashanski","score":"63 766 64"},{"winner_name":"Stefano Galvani","loser_name":"Jamie Baker","score":"64 62 63"},{"winner_name":"Guillermo Garcia-Lopez","loser_name":"Izak Van der Merwe","score":"75 62 62"},{"winner_name":"Marc Gicquel","loser_name":"Kei Nishikori","score":"46 75 (RET)"},{"winner_name":"Sebastien Grosjean","loser_name":"Potito Starace","score":"62 75 61"},{"winner_name":"Ernests Gulbis","loser_name":"John Isner","score":"75 75 673 766"},{"winner_name":"Tommy Haas","loser_name":"Guillermo Canas","score":"36 64 64 64"},{"winner_name":"Victor Hanescu","loser_name":"Alejandro Falla","score":"63 672 60 64"},{"winner_name":"Thomas Johansson","loser_name":"Vincent Spadea","score":"678 675 63 64 63"},{"winner_name":"Roko Karanusic","loser_name":"Luis Horna","score":"764 63 61"},{"winner_name":"Jesse Levine","loser_name":"Donald Young","score":"46 62 63 64"},{"winner_name":"Xavier Malisse","loser_name":"Denis Gremelmayr","score":"63 64 62"},{"winner_name":"Albert Montanes","loser_name":"Carlos Berlocq","score":"63 762 64"},{"winner_name":"Philipp Petzschner","loser_name":"Hyung-Taik Lee","score":"674 61 64 (RET)"},{"winner_name":"Bobby Reynolds","loser_name":"Filippo Volandri","score":"62 62 (RET)"},{"winner_name":"Olivier Rochus","loser_name":"Dudi Sela","score":"64 75 64"},{"winner_name":"Marat Safin","loser_name":"Fabio Fognini","score":"61 62 763"},{"winner_name":"Rainer Schuettler","loser_name":"Santiago Ventura","score":"63 62 64"},{"winner_name":"Florent Serra","loser_name":"Yen-Hsun Lu","score":"64 64 673 63"},{"winner_name":"Robin Soderling","loser_name":"Kevin Kim","score":"75 06 63 64"},{"winner_name":"Janko Tipsarevic","loser_name":"Thierry Ascione","score":"764 64 62"},{"winner_name":"Viktor Troicki","loser_name":"Nicolas Lapentti","score":"63 40 (RET)"},{"winner_name":"Martin Vassallo Arguello","loser_name":"Ivo Minar","score":"64 26 26 62 62"},{"winner_name":"Mischa Zverev","loser_name":"Alexander Peya","score":"63 64 64"}]},{"round":"Round of 64","Date":"2008-06-27","data":[{"winner_name":"Roger Federer","loser_name":"Robin Soderling","score":"63 64 763"},{"winner_name":"Rafael Nadal","loser_name":"Ernests Gulbis","score":"57 62 762 63"},{"winner_name":"Marat Safin","loser_name":"Novak Djokovic","score":"64 763 62"},{"winner_name":"David Ferrer","loser_name":"Igor Andreev","score":"36 63 64 62"},{"winner_name":"Janko Tipsarevic","loser_name":"Andy Roddick","score":"675 75 64 764"},{"winner_name":"Rainer Schuettler","loser_name":"James Blake","score":"63 678 46 64 64"},{"winner_name":"Richard Gasquet","loser_name":"Sebastien Grosjean","score":"62 62 (RET)"},{"winner_name":"Stan Wawrinka","loser_name":"Juan Martin del Potro","score":"765 63 75"},{"winner_name":"Andy Murray","loser_name":"Xavier Malisse","score":"64 62 62"},{"winner_name":"Guillermo Garcia-Lopez","loser_name":"Nicolas Almagro","score":"63 36 57 61 62"},{"winner_name":"Simone Bolelli","loser_name":"Fernando Gonzalez","score":"768 767 36 764"},{"winner_name":"Radek Stepanek","loser_name":"Viktor Troicki","score":"671 673 63 61 62"},{"winner_name":"Paul-Henri Mathieu","loser_name":"Jeremy Chardy","score":"63 75 761"},{"winner_name":"Mikhail Youzhny","loser_name":"Stefano Galvani","score":"46 64 63 36 63"},{"winner_name":"Tommy Haas","loser_name":"Tommy Robredo","score":"64 64 63"},{"winner_name":"Tomas Berdych","loser_name":"Victor Hanescu","score":"675 766 61 62"},{"winner_name":"Fernando Verdasco","loser_name":"Olivier Rochus","score":"764 675 61 61"},{"winner_name":"Mischa Zverev","loser_name":"Juan Carlos Ferrero","score":"64 64 21 (RET)"},{"winner_name":"Marcos Baghdatis","loser_name":"Thomas Johansson","score":"64 64 64"},{"winner_name":"Lleyton Hewitt","loser_name":"Albert Montanes","score":"764 60 62"},{"winner_name":"Marin Cilic","loser_name":"Jarkko Nieminen","score":"64 36 63 676 75"},{"winner_name":"Gilles Simon","loser_name":"Agustin Calleri","score":"57 62 63 64"},{"winner_name":"Andreas Seppi","loser_name":"Florent Serra","score":"63 674 62 675 64"},{"winner_name":"Dmitry Tursunov","loser_name":"Chris Eaton","score":"762 62 64"},{"winner_name":"Nicolas Kiefer","loser_name":"Martin Vassallo Arguello","score":"60 63 61"},{"winner_name":"Feliciano Lopez","loser_name":"Roko Karanusic","score":"63 63 64"},{"winner_name":"Mario Ancic","loser_name":"Philipp Petzschner","score":"61 64 671 46 63"},{"winner_name":"Arnaud Clement","loser_name":"Benjamin Becker","score":"767 763 63"},{"winner_name":"Marc Gicquel","loser_name":"Ilija Bozoljac","score":"46 57 761 76 63"},{"winner_name":"Jurgen Melzer","loser_name":"Jesse Levine","score":"46 62 36 64 61"},{"winner_name":"Bobby Reynolds","loser_name":"Frank Dancevic","score":"46 7610 64 64"},{"winner_name":"Simon Stadler","loser_name":"Thomaz Bellucci","score":"36 63 61 675 86"}]},{"round":"Round of 32","Date":"2008-06-28","data":[{"winner_name":"Roger Federer","loser_name":"Marc Gicquel","score":"63 63 61"},{"winner_name":"Rafael Nadal","loser_name":"Nicolas Kiefer","score":"763 62 63"},{"winner_name":"Mario Ancic","loser_name":"David Ferrer","score":"64 64 675 763"},{"winner_name":"Richard Gasquet","loser_name":"Gilles Simon","score":"63 63 673 63"},{"winner_name":"Stan Wawrinka","loser_name":"Mischa Zverev","score":"75 61 (RET)"},{"winner_name":"Andy Murray","loser_name":"Tommy Haas","score":"64 674 63 62"},{"winner_name":"Mikhail Youzhny","loser_name":"Radek Stepanek","score":"75 675 64 674 63"},{"winner_name":"Marin Cilic","loser_name":"Paul-Henri Mathieu","score":"675 63 64 767"},{"winner_name":"Fernando Verdasco","loser_name":"Tomas Berdych","score":"64 64 60"},{"winner_name":"Marcos Baghdatis","loser_name":"Simon Stadler","score":"762 64 62"},{"winner_name":"Lleyton Hewitt","loser_name":"Simone Bolelli","score":"61 63 762"},{"winner_name":"Marat Safin","loser_name":"Andreas Seppi","score":"765 36 763 64"},{"winner_name":"Janko Tipsarevic","loser_name":"Dmitry Tursunov","score":"761 763 63"},{"winner_name":"Feliciano Lopez","loser_name":"Bobby Reynolds","score":"64 75 46 64"},{"winner_name":"Arnaud Clement","loser_name":"Jurgen Melzer","score":"46 63 64 64"},{"winner_name":"Rainer Schuettler","loser_name":"Guillermo Garcia-Lopez","score":"62 63 64"}]},{"round":"Round of 16","Date":"2008-06-29","data":[{"winner_name":"Roger Federer","loser_name":"Lleyton Hewitt","score":"767 62 64"},{"winner_name":"Rafael Nadal","loser_name":"Mikhail Youzhny","score":"63 63 61"},{"winner_name":"Andy Murray","loser_name":"Richard Gasquet","score":"57 36 763 62 64"},{"winner_name":"Marat Safin","loser_name":"Stan Wawrinka","score":"64 63 57 61"},{"winner_name":"Mario Ancic","loser_name":"Fernando Verdasco","score":"36 46 63 64 1311"},{"winner_name":"Feliciano Lopez","loser_name":"Marcos Baghdatis","score":"57 62 36 764 86"},{"winner_name":"Arnaud Clement","loser_name":"Marin Cilic","score":"63 75 62"},{"winner_name":"Rainer Schuettler","loser_name":"Janko Tipsarevic","score":"64 36 64 764"}]},{"round":"Quarter-Finals","Date":"2008-06-30","data":[{"winner_name":"Roger Federer","loser_name":"Mario Ancic","score":"61 75 64"},{"winner_name":"Rafael Nadal","loser_name":"Andy Murray","score":"63 62 64"},{"winner_name":"Marat Safin","loser_name":"Feliciano Lopez","score":"36 75 761 63"},{"winner_name":"Rainer Schuettler","loser_name":"Arnaud Clement","score":"63 57 766 677 86"}]},{"round":"Semi-Finals","Date":"2008-07-01","data":[{"winner_name":"Roger Federer","loser_name":"Marat Safin","score":"63 763 64"},{"winner_name":"Rafael Nadal","loser_name":"Rainer Schuettler","score":"61 763 64"}]},{"round":"Final","Date":"2008-07-02","data":[{"winner_name":"Rafael Nadal","loser_name":"Roger Federer","score":"64 64 675 678 97"}]}]}]
