[{"round":"Final","rowid":7,"data":[{"winner_name":"Joao Menezes","loser_name":"Corentin Moutet","score":"762 767"}]},{"round":"Semifinals","rowid":6,"data":[{"winner_name":"Corentin Moutet","loser_name":"Andrej Martin","score":"64 06 62"},{"winner_name":"Joao Menezes","loser_name":"Sumit Nagal","score":"57 64 63"}]},{"round":"Quarterfinals","rowid":5,"data":[{"winner_name":"Corentin Moutet","loser_name":"Goncalo Oliveira","score":"62 52 (RET)"},{"winner_name":"Andrej Martin","loser_name":"Jose Hernandez-Fernandez","score":"64 46 62"},{"winner_name":"Joao Menezes","loser_name":"Uladzimir Ignatik","score":"62 64"},{"winner_name":"Sumit Nagal","loser_name":"Roberto Ortega-Olmedo","score":"75 64"}]},{"round":"Round of 16","rowid":4,"data":[{"winner_name":"Corentin Moutet","loser_name":"Pavel Kotov","score":"46 62 63"},{"winner_name":"Andrej Martin","loser_name":"Roberto Cid Subervi","score":"63 64"},{"winner_name":"Roberto Ortega-Olmedo","loser_name":"Lucas Miedler","score":"763 62"},{"winner_name":"Uladzimir Ignatik","loser_name":"Ulises Blanch","score":"765 672 765"},{"winner_name":"Goncalo Oliveira","loser_name":"Karim-Mohamed Maamoun","score":"64 64"},{"winner_name":"Jose Hernandez-Fernandez","loser_name":"Aleksandar Vukic","score":"765 63"},{"winner_name":"Sumit Nagal","loser_name":"Dmitry Popko","score":"767 63"},{"winner_name":"Joao Menezes","loser_name":"Denis Yevseyev","score":"63 61"}]},{"round":"Round of 32","rowid":3,"data":[{"winner_name":"Corentin Moutet","loser_name":"Antoine Escoffier","score":"16 63 61"},{"winner_name":"Dmitry Popko","loser_name":"Egor Gerasimov","score":"63 761"},{"winner_name":"Andrej Martin","loser_name":"Evgenii Tiurnev","score":"63 64"},{"winner_name":"Joao Menezes","loser_name":"Aleksandr Nedovyesov","score":"61 64"},{"winner_name":"Lucas Miedler","loser_name":"Carlos Boluda-Purkiss","score":"63 36 75"},{"winner_name":"Uladzimir Ignatik","loser_name":"Thiago Seyboth Wild","score":"765 46 62"},{"winner_name":"Goncalo Oliveira","loser_name":"Viktor Durasovic","score":"63 62"},{"winner_name":"Aleksandar Vukic","loser_name":"Guilherme Clezar","score":"75 64"},{"winner_name":"Jose Hernandez-Fernandez","loser_name":"Alexander Zhurbin","score":"64 677 62"},{"winner_name":"Ulises Blanch","loser_name":"Emil Ruusuvuori","score":"62 64"},{"winner_name":"Karim-Mohamed Maamoun","loser_name":"Roman Safiullin","score":"64 763"},{"winner_name":"Roberto Ortega-Olmedo","loser_name":"Sergey Fomin","score":"64 63"},{"winner_name":"Pavel Kotov","loser_name":"Teymuraz Gabashvili","score":"64 64"},{"winner_name":"Roberto Cid Subervi","loser_name":"Renzo Olivo","score":"36 62 63"},{"winner_name":"Sumit Nagal","loser_name":"Sadio Doumbia","score":"64 16 61"},{"winner_name":"Denis Yevseyev","loser_name":"Marcelo Arevalo","score":"766 36 63"}]},{"round":"Round of 64","rowid":2,"data":[{"winner_name":"Carlos Boluda-Purkiss","loser_name":"Andrey Golubev","score":"46 63 64"},{"winner_name":"Sadio Doumbia","loser_name":"Ivan Gakhov","score":"46 63 7611"},{"winner_name":"Viktor Durasovic","loser_name":"Brydan Klein","score":"64 36 63"},{"winner_name":"Antoine Escoffier","loser_name":"Sanjar Fayziev","score":"63 60"},{"winner_name":"Sergey Fomin","loser_name":"Khumoyun Sultanov","score":"763 36 62"},{"winner_name":"Teymuraz Gabashvili","loser_name":"Temur Ismailov","score":"61 60"},{"winner_name":"Karim-Mohamed Maamoun","loser_name":"Harry Bourchier","score":"62 763"},{"winner_name":"Joao Menezes","loser_name":"Olimjon Nabiev","score":"60 61"},{"winner_name":"Renzo Olivo","loser_name":"Illya Marchenko","score":"62 62"},{"winner_name":"Dmitry Popko","loser_name":"Jacob Grills","score":"63 763"},{"winner_name":"Emil Ruusuvuori","loser_name":"Fabrizio Ornago","score":"63 675 63"},{"winner_name":"Thiago Seyboth Wild","loser_name":"Arjun Kadhe","score":"60 63"},{"winner_name":"Evgenii Tiurnev","loser_name":"Vladyslav Manafov","score":"16 63 62"},{"winner_name":"Aleksandar Vukic","loser_name":"Peter Torebko","score":"61 60"},{"winner_name":"Denis Yevseyev","loser_name":"Alejandro Gonzalez","score":"63 673 64"},{"winner_name":"Alexander Zhurbin","loser_name":"Tobias Simon","score":"769 678 75"}]},{"round":"1st Round Qualifying","rowid":1,"data":[{"winner_name":"Evgenii Tiurnev","loser_name":"Anton Chekhov","score":"63 62"},{"winner_name":"Vladyslav Manafov","loser_name":"Sharobiddin Abzalov","score":"62 64"}]}]
